mvdh/__init__.py
mvdh/olsq_test.py
mvdh-0.1.7.dist-info/LICENSE
mvdh-0.1.7.dist-info/METADATA
mvdh-0.1.7.dist-info/WHEEL
mvdh-0.1.7.dist-info/top_level.txt
mvdh-0.1.7.dist-info/RECORD
