Metadata-Version: 2.1
Name: mvdh
Version: 0.1.7
Summary: Miscellaneous Python tools
Home-page: https://github.com/mvdh7/mvdh
Author: Matthew P. Humphreys
Author-email: m.p.humphreys@cantab.net
License: UNKNOWN
Platform: UNKNOWN
Classifier: Programming Language :: Python :: 3
Classifier: License :: OSI Approved :: MIT License
Classifier: Operating System :: OS Independent
Requires-Dist: autograd (==1.2)
